esiaccel-0.1.4.dist-info/entry_points.txt
esiaccel-0.1.4.dist-info/METADATA
esiaccel-0.1.4.dist-info/RECORD
esiaccel-0.1.4.dist-info/top_level.txt
esiaccel-0.1.4.dist-info/WHEEL
esiaccel-0.1.4.dist-info/licenses/LICENSE
esiaccel/__init__.py
esiaccel/codegen.py
esiaccel/accelerator.py
esiaccel/utils.py
esiaccel/esiCppAccel.cpython-310-x86_64-linux-gnu.so
esiaccel/types.py
esiaccel/lib/libMtiPli.so
esiaccel/lib/libESICppRuntime.so
esiaccel/lib/libEsiCosimDpiServer.so
esiaccel/lib/libCosimBackend.so
esiaccel/cmake/esiaccelConfig.cmake
esiaccel/include/esi/Types.h
esiaccel/include/esi/Common.h
esiaccel/include/esi/Ports.h
esiaccel/include/esi/Logging.h
esiaccel/include/esi/Engines.h
esiaccel/include/esi/Design.h
esiaccel/include/esi/Utils.h
esiaccel/include/esi/Manifest.h
esiaccel/include/esi/Accelerator.h
esiaccel/include/esi/Services.h
esiaccel/include/esi/Context.h
esiaccel/include/esi/CLI.h
esiaccel/include/esi/backends/Cosim.h
esiaccel/include/esi/backends/Trace.h
esiaccel/include/esi/backends/RpcServer.h
esiaccel/bin/esi-cosim.py
esiaccel/bin/esiquery
esiaccel/cosim/Cosim_Endpoint.sv
esiaccel/cosim/driver.cpp
esiaccel/cosim/driver.sv
esiaccel/cosim/Cosim_Manifest.sv
esiaccel/cosim/Cosim_DpiPkg.sv
